{"ret":200,"data":{"cityinfo":{"provinces":"四川","city":"成都","area":"武侯","id":"101270119","prov_py":"sichuan","city_py":"chengdu","qh":"028","jb":"3","yb":"610000","area_py":"wuhou","area_short_code":"wh","lng":"104.04303","lat":"30.64235"},"now":{"city":{"night_air_temperature":"23","day_air_temperature":"31","wind_direction":"微风","wind_power":"<3级","weather":"阵雨转大雨","weather_code":"03转09"},"id":"101270119","area_name":"武侯","detail":{"time":"10:50","date":"07月19日","week":"五","temperature":"28.5","wind_direction":"北风","wind_direction_str":"N","wind_power":"2级","wind_speed":"11km/h","humidity":"83%","weather":"阴","weather_code":"02","weather_english":"Overcast","njd":"6km","rain":"0","aqi":"21","quality":"优","ultraviolet_rays":"0级","ultraviolet_rays_status":null,"so2":"2","o3":"47","co":"1","no2":"9","aqi_pm25":"11","pm10":"19","nongli":"六月十四","sun_begin":"06:13","sun_end":"20:06"},"alarm_list":[{"province":"四川省","city":"","alarm_level":"蓝色","alarm_type":"暴雨","alarm_content":"四川省气象台2024年07月18日15时55分发布暴雨蓝色预警： 7月18日20时到19日20时：巴中、广元东部、南充北部、达州北部有大雨到暴雨（雨量30到80毫米），局地有大暴雨（120到150毫米），最大小时雨量30到50毫米。相关区域请注意强降雨引发的小流域山洪、地质灾害、中小河流洪水等风险的发生，注意预防。（预警信息来源：国家预警信息发布中心）","alarm_date":"2024-07-18 15:55:00"}],"update_time":1721358273}},"qt":0.025}